iufgbewroibgfowiebc/__init__.py
iufgbewroibgfowiebc-0.0.2.dist-info/METADATA
iufgbewroibgfowiebc-0.0.2.dist-info/WHEEL
iufgbewroibgfowiebc-0.0.2.dist-info/top_level.txt
iufgbewroibgfowiebc-0.0.2.dist-info/RECORD
