Metadata-Version: 2.1
Name: iufgbewroibgfowiebc
Version: 0.0.2
Summary: Dependency confiuse Attack
Author: <techghoshal>
Author-email: <techghoshal@gmail.com>
Requires-Dist: requests
